[
  {
    "variation": "default",
    "version": "sktwi1xtmkfgx8626",
    "items": [
      {}
    ],
    "primary": {
      "title": [
        {
          "type": "heading1",
          "text": "Beginning",
          "spans": []
        }
      ],
      "description": [
        {
          "type": "paragraph",
          "text": "Do cupidatat reprehenderit voluptate mollit commodo cupidatat culpa aliquip Lorem officia irure anim dolore reprehenderit. Magna occaecat adipisicing elit cillum ut veniam minim officia duis in qui cillum cillum.",
          "spans": []
        }
      ]
    },
    "slice_type": "cta_section"
  }
]